multi_exe_maker
