Metadata-Version: 2.1
Name: multi-exe-maker
Version: 0.4
Summary: This program can make a lot of executables files at the same time, in order to save time
Home-page: UNKNOWN
Author: Vitor Augusto de Lima Soares
Author-email: vitoraugustodelimasoares@gmail.com
License: UNKNOWN
Platform: UNKNOWN
